MANIFEST.in
README.md
setup.py
dash_color_picker/ColorPicker.py
dash_color_picker/__init__.py
dash_color_picker/_imports_.py
dash_color_picker/bundle.js
dash_color_picker/metadata.json
dash_color_picker/package.json
dash_color_picker.egg-info/PKG-INFO
dash_color_picker.egg-info/SOURCES.txt
dash_color_picker.egg-info/dependency_links.txt
dash_color_picker.egg-info/top_level.txt