Metadata-Version: 1.0
Name: dash-color-picker
Version: 0.0.1
Summary: React-color in Dash Original component: https://casesandberg.github.io/react-color/
Home-page: UNKNOWN
Author: Vivek Shankar vivekvs1@gmail.com
Author-email: UNKNOWN
License: MIT
Platform: UNKNOWN
